README.rst
setup.py
src/zc/__init__.py
src/zc.isithanging.egg-info/PKG-INFO
src/zc.isithanging.egg-info/SOURCES.txt
src/zc.isithanging.egg-info/dependency_links.txt
src/zc.isithanging.egg-info/entry_points.txt
src/zc.isithanging.egg-info/namespace_packages.txt
src/zc.isithanging.egg-info/not-zip-safe
src/zc.isithanging.egg-info/requires.txt
src/zc.isithanging.egg-info/top_level.txt
src/zc/isithanging/__init__.py
src/zc/isithanging/tests.py