Metadata-Version: 1.0
Name: zc.isithanging
Version: 0.3.0
Summary: A zc.monitor plugin for testing whether function hangs
Home-page: UNKNOWN
Author: Jim Fulton
Author-email: jim@zope.com
License: ZPL 2.1
Platform: UNKNOWN
